Workbook

Sheet Executive_Dashboard
B2: Strategic Investment Project: Executive Dashboard
B4: Scenario | C4: =Assumptions!C2 -> Base Case | H4: Projected Free Cash Flow
B6: Key Financial Metrics | C6: Project NPV: | D6: =Financial_Model!C21 -> -341182.61
C7: Project IRR: | D7: =Financial_Model!C22 -> 0.076621436
C8: Year 5 EBITDA: | D8: =Financial_Model!G8 -> 2704036.8
B10: Investment Decision | C10: =IF(Financial_Model!C21>=0,"ATTRACTIVE","NOT ATTRACTIVE") -> NOT ATTRACTIVE
B12: Break-even Analysis
B13: Revenue Growth Break-even | C13: 0.1178
B14: Revenue Growth Base Case | C14: 0.1
B15: Growth Gap | C15: =C13-C14 -> 0.0178
B16: WACC Break-even | C16: 0.0766
B17: WACC Base Case | C17: 0.1
B18: WACC Gap | C18: =C17-C16 -> 0.0234
B22: Sensitivity Analysis: NPV based on WACC and Revenue Growth
B23: =Assumptions!L4 -> -341182.61 | C23: =Assumptions!M4 -> -0.05 | D23: =Assumptions!N4 -> 0 | E23: =Assumptions!O4 -> 0.05 | F23: =Assumptions!P4 -> 0.1 | G23: =Assumptions!Q4 -> 0.15
B24: =Assumptions!L5 -> 0.08 | C24: =Assumptions!M5 -> -2761863.7 | D24: =Assumptions!N5 -> -1911211.5 | E24: =Assumptions!O5 -> -1024092.1 | F24: =Assumptions!P5 -> -51535.113 | G24: =Assumptions!Q5 -> 1012491.4
B25: =Assumptions!L6 -> 0.09 | C25: =Assumptions!M6 -> -2812297.6 | D25: =Assumptions!N6 -> -1992118 | E25: =Assumptions!O6 -> -1136831.4 | F25: =Assumptions!P6 -> -199575.16 | G25: =Assumptions!Q6 -> 825421.27
B26: =Assumptions!L7 -> 0.1 | C26: =Assumptions!M7 -> -2860871.1 | D26: =Assumptions!N7 -> -2069740.6 | E26: =Assumptions!O7 -> -1244799.1 | F26: =Assumptions!P7 -> -341182.61 | G26: =Assumptions!Q7 -> 646632
B27: =Assumptions!L8 -> 0.11 | C27: =Assumptions!M8 -> -2907674.7 | D27: =Assumptions!N8 -> -2144250.4 | E27: =Assumptions!O8 -> -1348250.5 | F27: =Assumptions!P8 -> -476706.88 | G27: =Assumptions!Q8 -> 475668.79
B28: =Assumptions!L9 -> 0.12 | C28: =Assumptions!M9 -> -2952793.8 | D28: =Assumptions!N9 -> -2215807.7 | E28: =Assumptions!O9 -> -1447424.4 | F28: =Assumptions!P9 -> -606474.98 | G28: =Assumptions!Q9 -> 312106.23

Sheet Story
B2: Strategic Investment Project: Investment Story
B4: 1. Business Context
B5: The company is evaluating a new premium healthy-food production and distribution facility to support future revenue growth and expand its operating capacity
B7: 2. Investment Opportunity
B8: The project requires an initial investment of THB 5.0 million and is expected to generate THB 5.0 million of revenue in Year 1.
B9: The Base Case assumes 10% annual revenue growth
B11: 3. Financial Case
B12: Initial CAPEX | E12: =Assumptions!C3 -> 5000000
B13: Base Case Revenue Growth | E13: =Assumptions!C5 -> 0.1
B14: WACC | E14: =Financial_Model!C20 -> 0.1
B15: NPV | E15: =Financial_Model!C21 -> -341182.61
B16: IRR | E16: =Financial_Model!C22 -> 0.076621436
B18: 4. Key Investment Insight
B19: The Base Case does not create sufficient economic value. NPV is negative at THB 341K and IRR of 7.66% is below the 10.00% required return.
B20: However, the project is relatively close to the investment threshold. NPV reaches approximately zero at around 11.78% revenue growth, compared with 10.00% in the Base Case.
B22: 5. Key Drivers, Risks & Upside
B23: Key Upside | D23: Revenue Growth: Higher-than-expected revenue growth is the main path to value creation. The project reaches NPV break-even at approximately 11.78% growth.
B24: Key Risk | D24: Cost of Capital: A higher WACC reduces project value. The project requires a WACC of approximately 7.66% or lower to achieve NPV break-even.
B26: 6. Investment Recommendation
B27: NOT ATTRACTIVE UNDER BASE CASE
B28: The project should not be approved under the current Base Case because NPV is negative and IRR is below WACC.
B29: However, management could reconsider the investment if the project can demonstrate stronger revenue growth, lower investment risk, or a lower cost of capital
B31: 7.Management Next Step
B32: Before approval, management should validate whether the project can realistically achieve revenue growth above the 11.78% break-even level
B33: and whether the required return can be reduced through lower investment risk or a more efficient capital structure.

Sheet Assumptions
B2: Active Scenario | C2: Base Case | G2: Base Case | H2: Best Case | I2: Worst Case | L2: Sensitivity Analysis: NPV based on WACC and Revenue Growth | V2: Working Capital Assumptions
B3: Initial CAPEX | C3: =CHOOSE(MATCH($C$2, {"Base Case","Best Case","Worst Case"}, 0), G3,H3,I3) -> 5000000 | F3: Initial CAPEX | G3: 5000000 | H3: 5000000 | I3: 5000000
B4: Revenue Year 1 | C4: =CHOOSE(MATCH($C$2, {"Base Case","Best Case","Worst Case"}, 0), G4,H4,I4) -> 5000000 | F4: Revenue Year 1 | G4: 5000000 | H4: 5500000 | I4: 4500000 | L4: =Financial_Model!C21 -> -341182.61 | M4: -0.05 | N4: 0 | O4: 0.05 | P4: 0.1 | Q4: 0.15
B5: Revenue Growth | C5: =CHOOSE(MATCH($C$2, {"Base Case","Best Case","Worst Case"}, 0),G5,H5,I5) -> 0.1 | F5: Revenue Growth | G5: 0.1 | H5: 0.15 | I5: 0.05 | L5: 0.08 | M5: -2761863.7 | N5: -1911211.5 | O5: -1024092.1 | P5: -51535.113 | Q5: 1012491.4
B6: COGS(% Revenue) | C6: =CHOOSE(MATCH($C$2, {"Base Case","Best Case","Worst Case"}, 0),G6,H6,I6) -> 0.4 | F6: COGS% Revenue | G6: 0.4 | H6: 0.35 | I6: 0.45 | L6: 0.09 | M6: -2812297.6 | N6: -1992118 | O6: -1136831.4 | P6: -199575.16 | Q6: 825421.27
B7: SG&A Year 1 | C7: =CHOOSE(MATCH($C$2, {"Base Case","Best Case","Worst Case"}, 0),G7,H7,I7) -> 1500000 | F7: SG&A Year 1 | G7: 1500000 | H7: 1400000 | I7: 1600000 | L7: 0.1 | M7: -2860871.1 | N7: -2069740.6 | O7: -1244799.1 | P7: -341182.61 | Q7: 646632
B8: Cost Inflation | C8: =CHOOSE(MATCH($C$2, {"Base Case","Best Case","Worst Case"}, 0),G8,H8,I8) -> 0.03 | F8: Cost Inflation | G8: 0.03 | H8: 0.02 | I8: 0.06 | L8: 0.11 | M8: -2907674.7 | N8: -2144250.4 | O8: -1348250.5 | P8: -476706.88 | Q8: 475668.79
B9: Tax Rate | C9: =CHOOSE(MATCH($C$2, {"Base Case","Best Case","Worst Case"}, 0),G9,H9,I9) -> 0.2 | F9: Tax Rate | G9: 0.2 | H9: 0.2 | I9: 0.2 | L9: 0.12 | M9: -2952793.8 | N9: -2215807.7 | O9: -1447424.4 | P9: -606474.98 | Q9: 312106.23
B10: Depreciation | C10: =CHOOSE(MATCH($C$2, {"Base Case","Best Case","Worst Case"}, 0),G10,H10,I10) -> 1000000 | F10: Depreciation | G10: 1000000 | H10: 1000000 | I10: 1000000
B11: CAPEX | C11: =CHOOSE(MATCH($C$2, {"Base Case","Best Case","Worst Case"}, 0),G11,H11,I11) -> 500000 | F11: CAPEX | G11: 500000 | H11: 450000 | I11: 600000
B12: NWC Requirement | C12: =CHOOSE(MATCH($C$2, {"Base Case","Best Case","Worst Case"}, 0),G12,H12,I12) -> 0.05 | F12: NWC Requirement | G12: 0.05 | H12: 0.05 | I12: 0.05
B13: WACC | C13: =CHOOSE(MATCH($C$2, {"Base Case","Best Case","Worst Case"}, 0),G13,H13,I13) -> 0.1 | F13: WACC | G13: 0.1 | H13: 0.08 | I13: 0.12
B14: Terminal Growth | C14: =CHOOSE(MATCH($C$2, {"Base Case","Best Case","Worst Case"}, 0),G14,H14,I14) -> 0 | F14: Terminal Growth | Q14: 0

Sheet Financial_Model
A1: Scenario
A2: =Assumptions!C2 -> Base Case
B3: Year 0 | C3: Year 1 | D3: Year 2 | E3: Year 3 | F3: Year 4 | G3: Year 5
A4: Revenue | B4: 0 | C4: =Assumptions!$C$4 -> 5000000 | D4: =C4*(1+Assumptions!$C$5) -> 5500000 | E4: =D4*(1+Assumptions!$C$5) -> 6050000 | F4: =E4*(1+Assumptions!$C$5) -> 6655000 | G4: =F4*(1+Assumptions!$C$5) -> 7320500
A5: COGS (40%) | B5: 0 | C5: =C4*Assumptions!$C$6 -> 2000000 | D5: =D4*Assumptions!$C$6 -> 2200000 | E5: =E4*Assumptions!$C$6 -> 2420000 | F5: =F4*Assumptions!$C$6 -> 2662000 | G5: =G4*Assumptions!$C$6 -> 2928200
A6: Gross Profit | B6: 0 | C6: =C4-C5 -> 3000000 | D6: =D4-D5 -> 3300000 | E6: =E4-E5 -> 3630000 | F6: =F4-F5 -> 3993000 | G6: =G4-G5 -> 4392300
A7: SG&A | B7: 0 | C7: =Assumptions!C7 -> 1500000 | D7: =C7 * (1 + Assumptions!$C$8) -> 1545000 | E7: =D7 * (1 + Assumptions!$C$8) -> 1591350 | F7: =E7 * (1 + Assumptions!$C$8) -> 1639090.5 | G7: =F7 * (1 + Assumptions!$C$8) -> 1688263.2
A8: EBITDA | B8: 0 | C8: =C6-C7 -> 1500000 | D8: =D6-D7 -> 1755000 | E8: =E6-E7 -> 2038650 | F8: =F6-F7 -> 2353909.5 | G8: =G6-G7 -> 2704036.8
A9: Depreciation | B9: 0 | C9: =Assumptions!$C$10 -> 1000000 | D9: =Assumptions!$C$10 -> 1000000 | E9: =Assumptions!$C$10 -> 1000000 | F9: =Assumptions!$C$10 -> 1000000 | G9: =Assumptions!$C$10 -> 1000000
A10: EBIT | B10: 0 | C10: =C8-C9 -> 500000 | D10: =D8-D9 -> 755000 | E10: =E8-E9 -> 1038650 | F10: =F8-F9 -> 1353909.5 | G10: =G8-G9 -> 1704036.8
A11: Taxes (20%) | B11: 0 | C11: =MAX(0, C10*Assumptions!$C$9) -> 100000 | D11: =MAX(0, D10*Assumptions!$C$9) -> 151000 | E11: =MAX(0, E10*Assumptions!$C$9) -> 207730 | F11: =MAX(0, F10*Assumptions!$C$9) -> 270781.9 | G11: =MAX(0, G10*Assumptions!$C$9) -> 340807.36
A12: NOPAT | B12: 0 | C12: =C10-C11 -> 400000 | D12: =D10-D11 -> 604000 | E12: =E10-E11 -> 830920 | F12: =F10-F11 -> 1083127.6 | G12: =G10-G11 -> 1363229.4
A13: Add: Depreciation | B13: 0 | C13: =C9 -> 1000000 | D13: =D9 -> 1000000 | E13: =E9 -> 1000000 | F13: =F9 -> 1000000 | G13: =G9 -> 1000000
A14: Less: CAPEX | B14: =-Assumptions!C3 -> -5000000 | C14: =-Assumptions!$C$11 -> -500000 | D14: =-Assumptions!$C$11 -> -500000 | E14: =-Assumptions!$C$11 -> -500000 | F14: =-Assumptions!$C$11 -> -500000 | G14: =-Assumptions!$C$11 -> -500000
A15: NWC | B15: 0 | C15: =C4*Assumptions!$C$12 -> 250000 | D15: =D4*Assumptions!$C$12 -> 275000 | E15: =E4*Assumptions!$C$12 -> 302500 | F15: =F4*Assumptions!$C$12 -> 332750 | G15: =G4*Assumptions!$C$12 -> 366025
A16: Less: Change in NWC | B16: 0 | C16: =-C15 -> -250000 | D16: =-(D15-C15) -> -25000 | E16: =-(E15-D15) -> -27500 | F16: =-(F15-E15) -> -30250 | G16: =-(G15-F15) -> -33275
A17: Free Cash Flow (FCF) | B17: =B12+B13+B14+B16 -> -5000000 | C17: =C12+C13+C14+C16 -> 650000 | D17: =D12+D13+D14+D16 -> 1079000 | E17: =E12+E13+E14+E16 -> 1303420 | F17: =F12+F13+F14+F16 -> 1552877.6 | G17: =G12+G13+G14+G16 -> 1829954.4
B19: Valuation Metrics
B20: WACC (Discount Rate) | C20: =Assumptions!$C$13 -> 0.1
B21: NPV | C21: =NPV(C20, C17:G17) + B17 -> -341182.61
B22: IRR | C22: =IRR(B17:G17) -> 0.076621436
B26: goal seek Reveune | C26: =C21 -> -341182.61
C27: 0.11777255
B28: goal seek WACC | C28: 0.076621436

Sheet PBI_Financials
A1: Scenario | B1: Year | C1: Revenue | D1: COGS | E1: Gross Profit | F1: SG&A | G1: EBITDA | H1: Depreciation | I1: EBIT | J1: Taxes | K1: NOPAT | L1: Add Depreciation | M1: CAPEX | N1: NWC | O1: Change in NWC | P1: FCF | Q1: WACC
A2: Base Case | B2: 0 | C2: 0 | D2: 0 | E2: 0 | F2: 0 | G2: 0 | H2: 0 | I2: 0 | J2: 0 | K2: 0 | L2: 0 | M2: -5000000 | N2: 0 | O2: 0 | P2: -5000000 | Q2: 0.1
A3: Base Case | B3: 1 | C3: 5000000 | D3: 2000000 | E3: 3000000 | F3: 1500000 | G3: 1500000 | H3: 1000000 | I3: 500000 | J3: 100000 | K3: 400000 | L3: 1000000 | M3: -500000 | N3: 250000 | O3: -250000 | P3: 650000 | Q3: 0.1
A4: Base Case | B4: 2 | C4: 5500000 | D4: 2200000 | E4: 3300000 | F4: 1545000 | G4: 1755000 | H4: 1000000 | I4: 755000 | J4: 151000 | K4: 604000 | L4: 1000000 | M4: -500000 | N4: 275000 | O4: -25000 | P4: 1079000 | Q4: 0.1
A5: Base Case | B5: 3 | C5: 6050000 | D5: 2420000 | E5: 3630000 | F5: 1591350 | G5: 2038650 | H5: 1000000 | I5: 1038650 | J5: 207730 | K5: 830920 | L5: 1000000 | M5: -500000 | N5: 302500 | O5: -27500 | P5: 1303420 | Q5: 0.1
A6: Base Case | B6: 4 | C6: 6655000 | D6: 2662000 | E6: 3993000 | F6: 1639090.5 | G6: 2353909.5 | H6: 1000000 | I6: 1353909.5 | J6: 270781.9 | K6: 1083127.6 | L6: 1000000 | M6: -500000 | N6: 332750 | O6: -30250 | P6: 1552877.6 | Q6: 0.1
A7: Base Case | B7: 5 | C7: 7320500 | D7: 2928200 | E7: 4392300 | F7: 1688263.2 | G7: 2704036.8 | H7: 1000000 | I7: 1704036.8 | J7: 340807.36 | K7: 1363229.4 | L7: 1000000 | M7: -500000 | N7: 366025 | O7: -33275 | P7: 1829954.4 | Q7: 0.1
A8: Best Case | B8: 0 | C8: 0 | D8: 0 | E8: 0 | F8: 0 | G8: 0 | H8: 0 | I8: 0 | J8: 0 | K8: 0 | L8: 0 | M8: -5000000 | N8: 0 | O8: 0 | P8: -5000000 | Q8: 0.08
A9: Best Case | B9: 1 | C9: 5500000 | D9: 1925000 | E9: 3575000 | F9: 1400000 | G9: 2175000 | H9: 1000000 | I9: 1175000 | J9: 235000 | K9: 940000 | L9: 1000000 | M9: -450000 | N9: 275000 | O9: -275000 | P9: 1215000 | Q9: 0.08
A10: Best Case | B10: 2 | C10: 6325000 | D10: 2213750 | E10: 4111250 | F10: 1428000 | G10: 2683250 | H10: 1000000 | I10: 1683250 | J10: 336650 | K10: 1346600 | L10: 1000000 | M10: -450000 | N10: 316250 | O10: -41250 | P10: 1855350 | Q10: 0.08
A11: Best Case | B11: 3 | C11: 7273750 | D11: 2545812.5 | E11: 4727937.5 | F11: 1456560 | G11: 3271377.5 | H11: 1000000 | I11: 2271377.5 | J11: 454275.5 | K11: 1817102 | L11: 1000000 | M11: -450000 | N11: 363687.5 | O11: -47437.5 | P11: 2319664.5 | Q11: 0.08
A12: Best Case | B12: 4 | C12: 8364812.5 | D12: 2927684.4 | E12: 5437128.1 | F12: 1485691.2 | G12: 3951436.9 | H12: 1000000 | I12: 2951436.9 | J12: 590287.39 | K12: 2361149.5 | L12: 1000000 | M12: -450000 | N12: 418240.62 | O12: -54553.125 | P12: 2856596.4 | Q12: 0.08
A13: Best Case | B13: 5 | C13: 9619534.4 | D13: 3366837 | E13: 6252697.3 | F13: 1515405 | G13: 4737292.3 | H13: 1000000 | I13: 3737292.3 | J13: 747458.46 | K13: 2989833.9 | L13: 1000000 | M13: -450000 | N13: 480976.72 | O13: -62736.094 | P13: 3477097.8 | Q13: 0.08
... A19: Worst Case | B19: 5 | C19: 5469778.1 | D19: 2461400.2 | E19: 3008378 | F19: 2019963.1 | G19: 988414.83 | H19: 1000000 | I19: -11585.167 | J19: 0 | K19: -11585.167 | L19: 1000000 | M19: -600000 | N19: 273488.91 | O19: -13023.281 | P19: 375391.55 | Q19: 0.12

Sheet PBI_Scenario_Summary
A1: Scenario | B1: WACC | C1: NPV | D1: IRR | E1: Year 5 Revenue | F1: Year 5 EBITDA | G1: Decision
A2: Base Case | B2: 0.1 | C2: -341182.61 | D2: 0.076621436 | E2: 7320500 | F2: 2704036.8 | G2: NOT ATTRACTIVE
A3: Best Case | B3: 0.08 | C3: 4023226 | D3: 0.30217308 | E3: 9619534.4 | F3: 4737292.3 | G3: ATTRACTIVE
A4: Worst Case | B4: 0.12 | C4: -4062244.2 | D4: -0.29047378 | E4: 5469778.1 | F4: 988414.83 | G4: NOT ATTRACTIVE
